skypydb/__init__.py
skypydb/errors.py
skypydb/api/__init__.py
skypydb/api/client.py
skypydb/api/collection.py
skypydb/api/dashboard_api.py
skypydb/api/vector_client.py
skypydb/cli/__init__.py
skypydb/cli/cli.py
skypydb/dashboard/rxconfig.py
skypydb/dashboard/dashboard/__init__.py
skypydb/dashboard/dashboard/dashboard.py
skypydb/db/__init__.py
skypydb/db/database.py
skypydb/db/vector_database.py
skypydb/embeddings/__init__.py
skypydb/embeddings/ollama.py
skypydb/schema/__init__.py
skypydb/schema/schema.py
skypydb/schema/values.py
skypydb/security/__init__.py
skypydb/security/encryption.py
skypydb/security/validation.py
skypydb/table/__init__.py
skypydb/table/table.py
skypydb-0.1.9.dist-info/licenses/LICENSE
skypydb-0.1.9.dist-info/METADATA
skypydb-0.1.9.dist-info/WHEEL
skypydb-0.1.9.dist-info/entry_points.txt
skypydb-0.1.9.dist-info/top_level.txt
skypydb-0.1.9.dist-info/RECORD
