Metadata-Version: 2.4
Name: skypydb
Version: 0.1.9
Summary: Open Source Reactive Database
Author: Ahen Studio
License-Expression: MIT
Project-URL: Homepage, https://github.com/Ahen-Studio/skypy-db
Project-URL: Bug Tracker, https://github.com/Ahen-Studio/skypy-db/issues
Classifier: Programming Language :: Python :: 3
Requires-Python: >=3.9
License-File: LICENSE
Requires-Dist: reflex>=0.8.25
Requires-Dist: uvicorn>=0.23.0
Requires-Dist: cryptography>=46.0.3
Requires-Dist: python-dotenv>=0.21.1
Requires-Dist: typer>=0.21.1
Requires-Dist: questionary>=2.0.1
Provides-Extra: mem0
Requires-Dist: mem0ai~=0.1.94; extra == "mem0"
Dynamic: license-file
